CHANGES.txt
README.txt
bootstrap.py
buildout.cfg
setup.py
src/hurry/__init__.py
src/hurry.extjs.egg-info/PKG-INFO
src/hurry.extjs.egg-info/SOURCES.txt
src/hurry.extjs.egg-info/dependency_links.txt
src/hurry.extjs.egg-info/namespace_packages.txt
src/hurry.extjs.egg-info/not-zip-safe
src/hurry.extjs.egg-info/requires.txt
src/hurry.extjs.egg-info/top_level.txt
src/hurry/extjs/__init__.py
src/hurry/extjs/basic.txt
src/hurry/extjs/configure.zcml
src/hurry/extjs/extjs.py
src/hurry/extjs/tests.py