Metadata-Version: 1.0
Name: hurry.extjs
Version: 2.2.1
Summary: ExtJS for hurry.resource.
Home-page: UNKNOWN
Author: Santiago Videla
Author-email: santiago.videla@gmail.com
License: ZPL 2.1
Platform: UNKNOWN
